numnorm.py
numnorm-1.1.1.dist-info/licenses/LICENSE
numnorm-1.1.1.dist-info/METADATA
numnorm-1.1.1.dist-info/WHEEL
numnorm-1.1.1.dist-info/top_level.txt
numnorm-1.1.1.dist-info/RECORD
