Metadata-Version: 2.4
Name: numnorm
Version: 1.1.1
Summary: Библиотека для безопасной универсальной нормализации альтернативных форматов ввода числовых данных — как в виде чисел, так и в виде строк с числовыми значениями — к стандартам записи чисел в Python и типизации их в int или float, а для случаев, когда входные данные не являются числовыми, библиотека гарантирует возврат данных с сохранением исходного типа и значения.
Home-page: https://gitverse.ru/Klimkov/numnorm
Author: Климков Максим
Author-email: Климков Максим <Klimkov@inbox.ru>
License: MIT
Project-URL: Homepage, https://gitverse.ru/Klimkov/numnorm
Project-URL: Repository, https://gitverse.ru/Klimkov/numnorm
Keywords: number,parsing,type-conversion,data-cleaning,robust
Classifier: Development Status :: 4 - Beta
Classifier: Intended Audience :: Developers
Classifier: License :: OSI Approved :: MIT License
Classifier: Programming Language :: Python :: 3
Classifier: Programming Language :: Python :: 3.13
Classifier: Topic :: Software Development :: Libraries
Classifier: Topic :: Utilities
Classifier: Typing :: Typed
Requires-Python: >=3.7
License-File: LICENSE
Dynamic: author
Dynamic: home-page
Dynamic: license-file
Dynamic: requires-python
